README.rst
setup.py
asyncdns/__init__.py
asyncdns/constants.py
asyncdns/darwin.py
asyncdns/dnssec.py
asyncdns/hosts.py
asyncdns/mdns.py
asyncdns/named.root
asyncdns/resolver.py
asyncdns/rr.py
asyncdns/smart.py
asyncdns/system.py
asyncdns/timeout.py
asyncdns/unix.py
asyncdns/utils.py
asyncdns/win32.py
asyncdns/wireformat.py
asyncdns2.egg-info/PKG-INFO
asyncdns2.egg-info/SOURCES.txt
asyncdns2.egg-info/dependency_links.txt
asyncdns2.egg-info/top_level.txt
scripts/pydig