Metadata-Version: 1.1
Name: asyncdns2
Version: 0.1.2
Summary: Pure Python asynchronous DNS via asyncio
Home-page: https://alastairs-place.net/projects/asyncdns
Author: Alastair Houghton
Author-email: alastair@alastairs-place.net
License: MIT License
Platform: UNKNOWN
Classifier: Development Status :: 4 - Beta
Classifier: License :: OSI Approved :: MIT License
Classifier: Topic :: Internet :: Name Service (DNS)
Classifier: Framework :: AsyncIO
Provides: asyncdns2
